egritools_kivy/__init__.py
egritools_kivy/__main__.py
egritools_kivy/change_extension_kv.py
egritools_kivy/combine_txt_kv.py
egritools_kivy/create_venv_kv.py
egritools_kivy/gpt2_trainer_kv.py
egritools_kivy/hf_upload_kv.py
egritools_kivy/preclean_gui_kv.py
egritools_kivy/wheel_manager_kv.py
egritools_kivy-0.2.0.dist-info/entry_points.txt
egritools_kivy-0.2.0.dist-info/licenses/LICENSE
egritools_kivy-0.2.0.dist-info/WHEEL
egritools_kivy-0.2.0.dist-info/METADATA
egritools_kivy-0.2.0.dist-info/RECORD
