Metadata-Version: 2.4
Name: egritools_kivy
Version: 0.2.0
Summary: Local utility toolkit by Egrigor86
Author-email: "Christopher (Egrigor86)" <egrigor86@gmail.com>
License-File: LICENSE
